setup.py
egen111222_fast_doc_example_app.egg-info/PKG-INFO
egen111222_fast_doc_example_app.egg-info/SOURCES.txt
egen111222_fast_doc_example_app.egg-info/dependency_links.txt
egen111222_fast_doc_example_app.egg-info/top_level.txt
project/program.py