Metadata-Version: 2.1
Name: egen111222-fast-doc-example-app
Version: 0.1
Summary: Python Distribution Utilities
Author: Kirill
Author-email: egen13@ukr.net
License: UNKNOWN
Platform: UNKNOWN
